nlp4ml/__init__.py
nlp4ml/encoder.py
nlp4ml/ensembler.py
nlp4ml/hypothesis.py
nlp4ml/main.py
nlp4ml/preprocessing.py
nlp4ml/search.py
nlp4ml/semantics.py
nlp4ml/statistics.py
nlp4ml/utils.py
nlp4ml/vectoriser.py
nlp4ml/visualiser.py
nlp4ml-0.1.24.dist-info/LICENSE.txt
nlp4ml-0.1.24.dist-info/METADATA
nlp4ml-0.1.24.dist-info/WHEEL
nlp4ml-0.1.24.dist-info/top_level.txt
nlp4ml-0.1.24.dist-info/RECORD
