Metadata-Version: 2.1
Name: nlp4ml
Version: 0.1.24
Summary: Python NLP wrapper
Home-page: https://github.com/penguinwang96825/nlp4ml.git
Author: Yang Wang
Author-email: penguinwang@smail.nchu.edu.tw
License: MIT
Platform: UNKNOWN
Requires-Dist: scikit-learn (==0.24.1)
Requires-Dist: pandas (==1.2.1)
Requires-Dist: numpy (==1.20.1)
Requires-Dist: xgboost (==1.3.3)
Requires-Dist: catboost (==0.24.4)
Requires-Dist: lightgbm (==3.1.1)
Requires-Dist: tqdm (==4.56.0)
Requires-Dist: gensim (==3.8.3)
Requires-Dist: matplotlib (==3.1.0)
Requires-Dist: seaborn (==0.9.0)
Requires-Dist: tweet-preprocessor (==0.6.0)
Requires-Dist: regex (==2020.11.13)
Requires-Dist: nlpaug (==0.0.9)
Requires-Dist: texttable (==1.6.3)
Requires-Dist: wordcloud (==1.8.1)
